retry7/__init__.py
retry7-0.0.2.dist-info/METADATA
retry7-0.0.2.dist-info/WHEEL
retry7-0.0.2.dist-info/top_level.txt
retry7-0.0.2.dist-info/RECORD
